bluesky_spreadsheet/__init__.py
bluesky_spreadsheet/_version.py
bluesky_spreadsheet/tests/__init__.py
bluesky_spreadsheet/tests/conftest.py
bluesky_spreadsheet/tests/test_examples.py
bluesky_spreadsheet-0.0.1.dist-info/METADATA
bluesky_spreadsheet-0.0.1.dist-info/RECORD
bluesky_spreadsheet-0.0.1.dist-info/WHEEL
bluesky_spreadsheet-0.0.1.dist-info/entry_points.txt
bluesky_spreadsheet-0.0.1.dist-info/top_level.txt
