Metadata-Version: 2.1
Name: bluesky-spreadsheet
Version: 0.0.1
Summary: Use a spreadsheet to input experiment procedures.
Home-page: https://github.com/bluesky/bluesky-spreadsheet
Author: Brookhaven National Lab
Author-email: dallan@bnl.gov
License: BSD (3-clause)
Platform: UNKNOWN
Classifier: Development Status :: 2 - Pre-Alpha
Classifier: Natural Language :: English
Classifier: Programming Language :: Python :: 3
Requires-Python: >=3.6
Requires-Dist: bluesky
Requires-Dist: openpyxl
Requires-Dist: pandas
Requires-Dist: xlrd
